setup.py
lazy_serializer/__init__.py
lazy_serializer/base.py
lazy_serializer/fields.py
lazy_serializer/validators.py
lazy_serializer.egg-info/PKG-INFO
lazy_serializer.egg-info/SOURCES.txt
lazy_serializer.egg-info/dependency_links.txt
lazy_serializer.egg-info/top_level.txt
tests/__init__.py
tests/__main__.py
tests/test_acceptance.py
tests/test_base_serializer.py