Metadata-Version: 1.1
Name: lazy-serializer
Version: 0.0.3
Summary: 
